networking_l2gw/__init__.py
networking_l2gw/_i18n.py
networking_l2gw/cmd/__init__.py
networking_l2gw/cmd/eventlet/__init__.py
networking_l2gw/cmd/eventlet/agent.py
networking_l2gw/db/__init__.py
networking_l2gw/db/l2gateway/__init__.py
networking_l2gw/db/l2gateway/db_query.py
networking_l2gw/db/l2gateway/head.py
networking_l2gw/db/l2gateway/l2gateway_db.py
networking_l2gw/db/l2gateway/l2gateway_models.py
networking_l2gw/db/l2gateway/ovsdb/__init__.py
networking_l2gw/db/l2gateway/ovsdb/lib.py
networking_l2gw/db/l2gateway/ovsdb/models.py
networking_l2gw/db/migration/__init__.py
networking_l2gw/db/migration/alembic_migrations/README
networking_l2gw/db/migration/alembic_migrations/__init__.py
networking_l2gw/db/migration/alembic_migrations/env.py
networking_l2gw/db/migration/alembic_migrations/script.py.mako
networking_l2gw/db/migration/alembic_migrations/versions/42438454c556_l2gateway_models.py
networking_l2gw/db/migration/alembic_migrations/versions/54c9c8fe22bf_db_models_for_ovsdb_hardware_vtep_schema.py
networking_l2gw/db/migration/alembic_migrations/versions/CONTRACT_HEAD
networking_l2gw/db/migration/alembic_migrations/versions/EXPAND_HEAD
networking_l2gw/db/migration/alembic_migrations/versions/__init__.py
networking_l2gw/db/migration/alembic_migrations/versions/kilo_release.py
networking_l2gw/db/migration/alembic_migrations/versions/start_networking_l2gw.py
networking_l2gw/db/migration/alembic_migrations/versions/liberty/contract/79919185aa99_initial_contract.py
networking_l2gw/db/migration/alembic_migrations/versions/liberty/expand/60019185aa99_initial_expand.py
networking_l2gw/db/migration/alembic_migrations/versions/newton/contract/2f533f7705dd_rename_tenant_to_project.py
networking_l2gw/db/migration/alembic_migrations/versions/newton/expand/49ce408ac349_add_indexes_to_tenant_id.py
networking_l2gw/db/migration/alembic_migrations/versions/queens/contract/0fb45e525aa9_add_standard_attribute_id_for_l2gw.py
networking_l2gw-21.0.0.dist-info/AUTHORS
networking_l2gw-21.0.0.dist-info/LICENSE
networking_l2gw-21.0.0.dist-info/METADATA
networking_l2gw-21.0.0.dist-info/WHEEL
networking_l2gw-21.0.0.dist-info/entry_points.txt
networking_l2gw-21.0.0.dist-info/pbr.json
networking_l2gw-21.0.0.dist-info/top_level.txt
networking_l2gw-21.0.0.dist-info/RECORD
