Metadata-Version: 2.1
Name: networking-l2gw
Version: 21.0.0
Summary: APIs and implementations to support L2 Gateways in Neutron.
Home-page: https://opendev.org/x/networking-l2gw
Author: OpenStack
Author-email: openstack-discuss@lists.openstack.org
Classifier: Environment :: OpenStack
Classifier: Intended Audience :: Information Technology
Classifier: Intended Audience :: System Administrators
Classifier: License :: OSI Approved :: Apache Software License
Classifier: Operating System :: POSIX :: Linux
Classifier: Programming Language :: Python
Classifier: Programming Language :: Python :: Implementation :: CPython
Classifier: Programming Language :: Python :: 3 :: Only
Classifier: Programming Language :: Python :: 3
Classifier: Programming Language :: Python :: 3.9
Classifier: Programming Language :: Python :: 3.10
Classifier: Programming Language :: Python :: 3.11
Classifier: Programming Language :: Python :: 3.12
Requires-Python: >=3.9
License-File: LICENSE
License-File: AUTHORS
Requires-Dist: pbr >=4.0.0
Requires-Dist: neutron-lib >=3.1.0
Requires-Dist: python-neutronclient >=7.8.0
Requires-Dist: ovsdbapp >=1.16.0
Requires-Dist: neutron >=26.0.0
